reCBZ/__init__.py
reCBZ/__main__.py
reCBZ/archive.py
reCBZ/config.toml
reCBZ/formats.py
reCBZ/wrappers.py
reCBZ-2.0.0.dist-info/LICENSE
reCBZ-2.0.0.dist-info/METADATA
reCBZ-2.0.0.dist-info/WHEEL
reCBZ-2.0.0.dist-info/entry_points.txt
reCBZ-2.0.0.dist-info/top_level.txt
reCBZ-2.0.0.dist-info/RECORD
