Metadata-Version: 2.1
Name: reCBZ
Version: 2.0.0
Summary: Utility for repacking and optmizing manga & comic archives
License: GPLv3
Project-URL: Homepage, https://github.com/avalonv/reCBZ
Keywords: manga,comics,cbz,ebooks
Classifier: License :: OSI Approved :: GNU General Public License v3 (GPLv3)
Classifier: Programming Language :: Python
Classifier: Programming Language :: Python :: 3
Classifier: Topic :: Scientific/Engineering :: Image Processing
Classifier: Topic :: System :: Archiving
Classifier: Topic :: System :: Archiving :: Compression
Classifier: Topic :: Utilities
Requires-Python: >=3.7
License-File: LICENSE
Requires-Dist: pillow (>=8)
Requires-Dist: tomli ; python_version < "3.11"
Provides-Extra: dev
Requires-Dist: bumpver ; extra == 'dev'
Requires-Dist: pip-tools ; extra == 'dev'
